{
  "source": "linkedin",
  "url": "https://at.linkedin.com/jobs/view/backend-web-developer-m-w-d-at-eurofunk-kappacher-gmbh-4321627839",
  "title": "BACKEND WEB DEVELOPER (m/w/d)",
  "company": "eurofunk Kappacher GmbH",
  "location": "Linz (Stadt), Oberösterreich, Österreich",
  "description": "- Hagenberg im Mühlkreis\n- Klagenfurt\n- Linz\n- Salzburg\n- St. Johann im Pongau\n- Berufserfahrung\n- Vollzeit\n\nALL ABOUT: CREATING SAFETY BY TECHNOLOGY\n\nSinnstiftend, nachhaltig und agil. Vernetzt, innovativ und modern. Einzigartig, dynamisch und international.\n\nMit 360°-Kommunikations- und Leitstellenlösungen schaffen wir Sicherheit.\n\nEinsatzorganisationen, Industriekunden und internationale Flughäfen zählen zu unserem Kundenportfolio.\n\nIn der Symbiose aus Innovation, Qualität und modernster Technologie mit nachhaltigem Nutzen schaffen wir für die Notrufannahme, die Einsatzmitteldisposition und die Alarmierung hochverfügbare, innovative technische Lösungen.\n\nDEIN BEITRAG\n\n- Entwerfe und entwickle robuste, skalierbare Java 21-Dienste mit Spring Boot 3 für hochverfügbare Lösungen.\n- Nutze moderne Backend-Technologien wie Elasticsearch, Redis, RabbitMQ und relationale Datenbanken.\n- Arbeite aktiv am Design der Software-Architektur mit und sorge dafür, dass die Backend-Dienste zukunftssicher sind.\n- Stelle die Zuverlässigkeit und Wartbarkeit des Codes durch rigorose Tests und bewährte Verfahren sicher.\n- Arbeite in einem funktionsübergreifenden, agilen Teamumfeld und setze Tools wie Git, Jira und Confluence ein.\n- Engagiere dich für kontinuierliches Lernen, teile dein Wissen und unterstütze dein Team dabei, gemeinsam die bestmöglichen Ergebnisse zu erzielen.\n\nDEINE PERSPEKTIVE\n\n- Sinnstiftende Arbeit & Innovation: Werde Teil eines krisensicheren Familienunternehmens, unterstütze lebensrettende Organisationen und arbeite mit modernsten Technologien, um gemeinsam etwas zum großen Ganzen beizutragen.\n- Gemeinschaft & Vielfalt: Flache Hierarchien, multikulturelle und dynamische Teams sowie regelmäßige Teamaktivitäten und Company Events stärken den Zusammenhalt - gemeinsam feiern wir unsere Erfolge!\n- Flexibilität & Teamspirit: Gleitzeit und bis zu 2 Home-Office-Tage pro Woche - wir schätzen den persönlichen Austausch im Team vor Ort.\n- Weiterentwicklung: Lerne und wachse mit der eurofunk Academy, Tech.Talks und individuellem Mentoring.\n- Gesundheit & Nachhaltigkeit: Fitnessangebote und Mittagessen sowie betriebliche Gesundheitsförderung. EcoVadis-zertifizierte Nachhaltigkeit, CO₂-Kompensation und umweltfreundliche Mobilitätsangebote.\n- Erreichbarkeit: Kostenlose Parkplätze und perfekte Zuganbindung\n- Moderne Arbeitsumgebung: Genieße moderne Räumlichkeiten und ergonomische Büroausstattung sowie durchdachte Spaces wie Workout.Zone und Game.Zone.\n\nAufgrund gesetzlicher Vorgaben sind wir verpflichtet, darauf hinzuweisen, dass das Mindestgehalt für diese Position ab einem Bruttojahresgehalt von € 55.356 startet. Wir bieten eine Überzahlung (auch deutliche) je nach individueller Qualifikation und Berufserfahrung.\n\nWERDE TEIL UNSERES TEAMS IN EINEM ZUKUNFTSSICHEREN UNTERNEHMEN UND HILF MIT, LEBEN ZU RETTEN!\n\n- Andreas Tiede\n- HR Business Partner",
  "postedAt": "2025-11-10",
  "id": "76e70f9b27ff2634",
  "status": "uncertain",
  "scrapedAt": "2026-07-14T11:44:34.656Z",
  "updatedAt": "2026-07-14T13:06:52.018Z",
  "match": null
}