{
  "source": "linkedin",
  "url": "https://at.linkedin.com/jobs/view/full%C2%ADstack-engi%C2%ADneer-m-w-d-at-bwt-group-4403615827",
  "title": "Full­stack Engi­neer (m/w/d)",
  "company": "BWT Group",
  "location": "Mondsee, Oberösterreich, Österreich",
  "description": "Ihre Aufgaben\n\n- Entwick­lung und Wartung cloud­ba­sierter Produkt‑ und Kunden­ma­nage­ment‑Platt­formen (Mobile Apps, Web Apps, IoT‑Backends, APIs und ereig­nis­ge­steu­erter Systeme)\n- Mitar­beit über den gesamten Soft­ware‑Lebens­zy­klus hinweg – von Anfor­de­rungs­ana­lyse und Archi­tektur über Imple­men­tie­rung bis hin zu Release und Betrieb\n- Entwick­lung von Backend‑ und Frontend‑Kompo­nenten mit Fokus auf saubere Schnitt­stellen und ein konsis­tentes Benut­zer­er­lebnis\n- Recherche, Bewer­tung und Einfüh­rung neuer Tech­no­lo­gien und Lösungen zur konti­nu­ier­li­chen Weiter­ent­wick­lung unserer Produkte und Platt­formen, einschließ­lich KI‑unter­stützter Entwick­lung\n- Enge Zusam­men­ar­beit und Wissens­aus­tausch in einem funk­ti­ons­über­grei­fenden, inter­na­tio­nalen Engi­nee­ring‑Team\n\nIhr Profil\n\n- Mindes­tens 2 Jahre Berufs­er­fah­rung in der Web‑basierten Soft­ware­ent­wick­lung\n- Erfah­rung in der Backend‑Entwick­lung mit C# / .NET oder vergleich­baren Tech­no­lo­gien\n- Praxis in der Entwick­lung von RESTful APIs sowie im Umgang mit Daten­for­maten wie JSON oder Protobuf\n- Prak­ti­sche Erfah­rung mit NoSQL‑Daten­banken (z. B. MongoDB)\n- Kennt­nisse in der Frontend‑Entwick­lung, idea­ler­weise mit React und TypeScript\n- Idea­ler­weise Erfah­rung mit IoT‑Platt­formen und ‑Proto­kollen (z. B. Azure IoT, MQTT, AMQP, RabbitMQ), GraphQL, Cloud‑Infra­struktur sowie Cloud‑nativer Entwick­lung\n- Zusätz­liche Stärken sind Kennt­nisse von Git‑basierten Entwick­lungs‑Work­flows, CI/CD‑Pipe­lines und DevOps‑Prak­tiken\n- Sehr gute Deutsch- und gute Englisch­kennt­nisse\n\nUnser Angebot\n\n- ABWECHS­LUNG & VERANT­WOR­TUNG: ein span­nendes Aufga­ben­ge­biet mit Eigen­ver­ant­wor­tung, Gestal­tungs­spiel­raum und abwechs­lungs­rei­chen Heraus­for­de­rungen\n- FLEXI­BLES ARBEITEN: Gleit­zeit­mo­dell sowie eine begrenzte Homeoffice- Möglichkeit für mehr Flexi­bi­lität im Arbeits­alltag\n- ENTWICK­LUNG & KARRIERE: indi­vi­du­elle Karrie­re­mög­lich­keiten sowie maßge­schnei­derte Aus- und Weiter­bil­dungs­an­ge­bote zur persön­li­chen und fach­li­chen Weiter­ent­wick­lung\n- ATTRAK­TIVE BENE­FITS: kosten­freier Obst­korb sowie Kaffee, Tee und Wasser, BWT- Kantine inklu­sive Essens­zu­schuss, attrak­tive Mitar­bei­ter­ra­batte im BWT- Onlineshop, Corpo­rate Bene­fits sowie ein Park­haus direkt vor Ort\n- GEMEIN­SAME ERLEB­NISSE: regel­mä­ßige Firmen­events wie Sommer­fest und Weih­nachts­feier sorgen für echten Team­spirit\n- STABI­LITÄT & PERSPEK­TIVE: Sicherer Arbeits­platz in einem stabil wach­senden, inter­na­tional tätigen Unter­nehmen mit flachen Hier­ar­chien und kurzen Entschei­dungs­wegen\n- Das Jahres­brut­to­ge­halt beträgt lt. Kollek­tiv­ver­trag mind. EUR 47.516,-. Für Sie schnüren wir jedoch ein attrak­tives Gehalts­paket, das Ihre Exper­tise und Erfah­rung berück­sich­tigt",
  "postedAt": "2026-05-10",
  "id": "7322db09e91bdbee",
  "status": "uncertain",
  "scrapedAt": "2026-07-14T11:44:34.659Z",
  "updatedAt": "2026-07-15T11:45:52.383Z",
  "match": null,
  "fit": null
}