{
  "source": "linkedin",
  "url": "https://at.linkedin.com/jobs/view/full-stack-web-developer-m-w-x-at-ev-group-4295645097",
  "title": "Full Stack / Web Developer (m/w/x)",
  "company": "EV Group",
  "location": "Sankt Florian am Inn, Oberösterreich, Österreich",
  "description": "Wenn du Freude daran hast, sowohl Backend als auch Frontend gemeinsam zu entwickeln und keine Scheu davor hast, tief in komplexe Analysen und Benutzeroberflächen einzutauchen, um sie nutzerfreundlich zu gestalten und aufzubereiten, dann haben wir die perfekte Position für dich!\n\nWir suchen einen Full Stack Developer, der eine Leidenschaft fürs Detail mitbringt und Freude an technischen Lösungen hat. In einem interdisziplinären Scrum-Team wirst du uns bei der Neu- und Weiterentwicklung unterstützen und einen entscheidenden Beitrag leisten.\n\nBei uns sind Berufs- und Quereinsteiger herzlich willkommen. Deine Leidenschaft und Bereitschaft, Neues zu lernen, sind für uns entscheidend.\n\nAls Arbeitsort ist neben unserem Headquarter in St. Florian am Inn (bei Schärding) auch unser Standort im TechnoZ in Braunau oder unser Büro im Tech Harbor in Linz möglich – je nachdem welcher Standort für dich am besten ist. Damit du auch gut ins Team und in deine neuen Aufgaben starten kannst, findet die Einarbeitung größtenteils am Headquarter in St. Florian am Inn statt.\n\nWas dich erwartet:\n\n- Entwicklung von Full Stack Applikationen mit C# und ASP.Net Core Blazor\n- Entwicklung von Web Apps auf Basis von Applikationsplattformen (bspw. K2, Sharepoint, Omnitracker) oder Individualentwicklung\n- vom Konzept bis zum Endprodukt involviert sein – Planung, Projektierung, Entwicklung für unsere Produkte mit Web-Technologien\n- konstruktive Mitarbeit in Entwicklungs- und Scrum-Teams\n- Transparenz und Flexibilität durch agile Entwicklungsansätze und Teamarbeitsmethoden\n\nWas du mitbringst:\n\n- eine abgeschlossene Ausbildung (Berufsausbildung/Lehrabschluss, HTL oder FH/Universität) im Bereich Informatik oder entsprechende Berufserfahrung mit Schwerpunkt auf Webentwicklung\n- Kenntnisse in der Full Stack- oder Webentwicklung von Vorteil\n- Grundsätzliche Programmierkenntnisse, Kenntnisse im Bereich C#, .Net, Java, Java Script wünschenswert\n- Kenntnisse im Bereich Applikationsentwicklung mit Sharepoint, K2 oder Omnitracker von Vorteil\n- Analytisch-logisches Denkvermögen und Genauigkeit\n- Begeisterung für die Lösung von komplexen Aufgaben\n- gute Englischkenntnisse\n\nGehalt:\n\nÜbers Gehalt sprechen wir am liebsten persönlich, aber so viel können wir schonmal verraten: Wir orientieren uns selbstverständlich an marktüblichen Gehältern - das heißt, abhängig von der Position und Ausbildung ist bereits beim Einstieg eine Überbezahlung zum Kollektivvertrag möglich. Für diese Position bieten wir ein jährliches Bruttogehalt von mindestens 45.500 EUR. Je nach Qualifikation und Erfahrung gibt’s entsprechend auch mehr!",
  "postedAt": "2025-09-04",
  "id": "4710c753bab2cc7b",
  "status": "uncertain",
  "scrapedAt": "2026-07-09T11:05:56.946Z",
  "updatedAt": "2026-07-09T11:11:42.706Z",
  "match": null
}