{
  "source": "ams",
  "url": "https://jobs.ams.at/public/emps/jobs/22223182",
  "title": "IT-Administration (w/m/d)",
  "company": "HR Personalmanagement GmbH",
  "location": "Traun",
  "description": "Tätigkeitsbereich:\n\n·        Pflege und Weiterentwicklung des Inhouse-Tools „SES“\n\n·        Support für Hard- und Software sowie Microsoft 365/ Windows 11\n\n·        Schnittstelle zwischen zentralem IT- Support und lokalem Team\n\n·        Mitarbeit bei IT- Projekten und neuen Strategien\n\n·        Unterstützung im 2nd-Level-Support\n\n·        Dokumentation und Verwaltung von Hard- und Software\n\n·        Unterstützung bei KPI- Erfassung\n\nANFORDERUNGSPROFIL:\n\n·         Informatik- Ausbildung oder vergleichbare Erfahrung\n\n·         Kenntnisse in C# (ASP.NET), JavaScript/ TypeScript, HTML und CSS\n\n·         Grundkenntnisse in MS SQL oder Oracle von Vorteil\n\n·         Führerschein und Auto\n\nARBEITSORT:\n4600 Wels\n\nBeschäftigungsausmaß:\n38,5 Stunden/Woche\n\nWIR BIETEN:\n\nDas kollektivvertragliche Mindestentgelt brutto beträgt 3500,00 Euro (exkl. Zulagen oder Überstunden) für diese Position.\n\nDie für die Beschäftigung maßgeblichen Rahmenbedingungen orientieren sich bei HR Personalmanagement selbst aber auch bei seinem Kunden dort, wo es einen Kollektivvertrag gibt an diesem, sonst an den marktüblichen Rahmenbedingungen und Konditionen. Die Höhe liegt über dem Kollektivvertragsniveau.\n\nSelbstverständlich behandeln wir Ihre Bewerbung vertraulich und gemäß den Bestimmungen des Gleichbehandlungsgesetzes. Bei allen Angeboten werden bei HR Personalmanagement Frauen und Männer gleichermaßen angesprochen und bei vergleichbarer Qualifikation und Berufserfahrung gleich entlohnt!\n\nBitte haben Sie Verständnis, dass wir etwaige, Ihnen mit der Wahrnehmung von Vorstellungsgesprächen in unserem Hause verbundenen Kosten, nicht übernehmen können.\n\nIhre schriftlichen Bewerbungsunterlagen übersenden Sie bitte per Post oder per E-Mail. Terminvereinbarung unter der Tel:  0732-211235-30\n\nHR Personalmanagement GmbH\n\nBreitwiesergutstraße 10\n\n4020 Linz\n\nTel: 0732-211235-0\n\nFax: 0732-211235-90\n\ne-mail: jobs@hr-personalmanagement.at\n\nwww.hr-personalmanagement.at",
  "postedAt": "2026-06-08T00:00:00Z",
  "id": "4242d3d460d8ff1e",
  "status": "uncertain",
  "scrapedAt": "2026-07-14T11:44:34.716Z",
  "updatedAt": "2026-07-15T11:45:52.393Z",
  "match": null,
  "fit": null
}