{
  "source": "ams",
  "url": "https://jobs.ams.at/public/emps/jobs/22304131",
  "title": "IT-Systemtechniker",
  "company": "Sonnleitner GmbH & Co KG",
  "location": "Österreich",
  "description": "Deine Rolle im Team\n1st und 2nd Level-Support (Annahme, Bearbeitung und Beantwortung von Anfragen und Fehlermeldungen)\nHard- und Softwarebereitstellung\nErfassung, Priorisierung, Bearbeitung und Weiterleitung von Fehler- und Störungsmeldungen im Ticketsystem\n\nUnser Angebot\nArbeitsplatz mit idealer öffentlicher Anbindung, Parkplatz und guter Infrastruktur\nInnovatives digitales Arbeitsumfeld am neuesten Stand der Technik\nEine langfristige und sichere Perspektive mit Festanstellung in einem etablierten und wachsenden Familienbetrieb\nAnspruchs- und verantwortungsvolle Tätigkeiten (38,5 Wochenstunden) in einem breiten, abwechslungsreichen und spannenden Arbeitsumfeld\nPermanente Fort- und Weiterbildungsmöglichkeiten\nEin strukturiertes Einarbeitungskonzept durch erfahrene Kollegen\nFlache Hierarchien, kurze Entscheidungswege\nEin dynamisches Team, in dem Arbeiten Spaß macht\nFür diese Position gilt, auf Basis einer Vollzeitbeschäftigung (38,5 Wochenstunden), das Mindestgehalt lt. KV des Metallgewerbes. Die tatsächliche Entlohnung richtet sich nach der Berufserfahrung und der Qualifikation.\n\nUnsere Erwartungen an dich:\nQualifikationen\nBreites IT-Verständnis und hohe technische Kompetenz\nSehr gute Kenntnisse von Office-Anwendungen, Betriebssystemen, E-Mail Clients, Browsern, etc.\nSehr gute Kommunikationsfähigkeit (Telefon, E-Mail, etc.) und starke Teamfähigkeit\nLösungsorientierte Denkweise, Belastbarkeit und Flexibilität\n\nErfahrung\nMehrjährige relevante Berufserfahrung von Vorteil\n\nAusbildung\nAbgeschlossene technische Ausbildung im Bereich IT",
  "postedAt": "2026-06-12T13:39:08Z",
  "id": "d0398d65e6dbcf19",
  "status": "uncertain",
  "scrapedAt": "2026-07-14T11:44:34.737Z",
  "updatedAt": "2026-07-14T13:06:52.069Z",
  "match": null
}