{
  "source": "jobs.at",
  "url": "https://www.jobs.at/i/7847742",
  "title": "Student (m/w/d) für eine Studien- oder Abschlussarbeit im Bereich Elektronik, Softwareentwicklung, Mechatronik, Maschinenbau, Mobilhydraulik, Konstruktion",
  "company": "Wacker Neuson Linz GmbH",
  "location": "Hörsching",
  "description": "<p>Verst&auml;rken Sie uns <strong>ab Fr&uuml;hjahr 2026</strong> als  </p>\n<h2>Student (m/w/d) f&uuml;r eine Studien- oder Abschlussarbeit im Bereich Elektronik, Softwareentwicklung, Mechatronik, Maschinenbau, Mobilhydraulik, Konstruktion</h2>\n<h3>Ihre Aufgaben bei uns</h3>\n<p>Durch Ihre Arbeit bekommen Sie einen intensiven Einblick in die T&auml;tigkeit als EntwicklerIn und lernen das Zusammenspiel unterschiedlicher Bereiche des Unternehmens kennen. Sie k&ouml;nnen Ihr Wissen aktiv einbringen und sich anhand der Bearbeitung eines interessanten, abwechslungsreichen und verantwortungsvollen Projekts fachlich und pers&ouml;nlich weiterqualifizieren. Ihre Betreuung erfolgt durch AnsprechpartnerInnen in den Fachabteilungen sowie durch ein Mentoringprogramm.  </p>\n<h4>Das bringen Sie mit</h4>\n<p>Sie absolvieren derzeit ein <strong>technisches Studium</strong> (z. B. Maschinenbau, Elektronik, Softwareentwicklung, Mechatronik, o.&auml;.), m&ouml;chten dies mit einer praxisnahen Studien- oder <strong>Abschlussarbeit </strong>beenden und haben 6 Monate Zeit, in Vollzeit, ein Praktikum zu absolvieren. <br> <br> Sie haben Interesse an der Entwicklung von Baumaschinen. Im Umgang mit MS-Office Produkten sind Sie ge&uuml;bt. Kommunikationsf&auml;hige Deutsch- und Englischkenntnisse runden Ihr Profil ab. In der Forschung und Entwicklung ist nicht nur ein sehr gutes theoretisches Wissen gefragt, sondern Kreativit&auml;t und Freude an der Entwicklung innovativer L&ouml;sungen.  </p>\n<p>F&uuml;r dieses Praktikum bieten wir Ihnen ein kollektivvertragliches Praktikumsgehalt von EUR 1.949,22 brutto/Monat. <br> Bei Bewerbung bitte Lebenslauf, Anschreiben, aktuellen Notenspiegel und geplanten Praktikumszeitraum anf&uuml;hren.  </p>\n<p>Willkommen bei der Wacker Neuson Group, einem international erfolgreichen Konzern im Bereich Bauger&auml;te, Kompaktmaschinen und Dienstleistungen. Im Jahr 2025 haben weltweit rund 5.800 Mitarbeitende zu unserem Erfolg beigetragen und dabei rund 2,2 Mrd. Euro Umsatz erwirtschaftet. Mit unseren Marken Wacker Neuson, Kramer, Weidemann und Enar erf&uuml;llen wir die hohen Anforderungen unserer unterschiedlichen Zielgruppen und Kundensegmente. Alles, was unsere Kunden f&uuml;r ihre anspruchsvollen Projekte ben&ouml;tigen, finden sie bei uns. Alles, was wir zur Erreichung unserer ambitionierten Ziele ben&ouml;tigen, sind Originale wie Sie!  </p>\n<h4>Was wir Ihnen bieten</h4>\n<ul>\n<li>Wir st&auml;rken uns gegenseitig: <strong>Teamgeist</strong> ist unsere Superpower  </li>\n<li><strong>Open Culture</strong>: Immer ein Ohr f&uuml;r Ideen und Raum, diese zu verwirklichen  </li>\n<li><strong>Vision&auml;re Projekte</strong>, die auf Input warten  </li>\n<li><strong>Alles in Balance</strong>: Flexible Arbeitszeiten (Gleitzeit ohne Kernzeit)  </li>\n<li><strong>F&uuml;r Kochmuffel</strong>: In unserem Mitarbeiterrestaurant gibt es jeden Tag frisches und gesundes Essen  </li>\n<li><strong>Fit for Future</strong>: Mit Sportangeboten, Bike-Leasing, Betriebs&auml;rzt:innen und gesunden Snacks bleiben wir zusammen fit  </li>\n</ul>\n<p>Sind Sie unser Original? Dann werden Sie Teil der Wacker Neuson Group.  </p>\n<p>Jetzt bewerben!  </p>\n<p>Ihr pers&ouml;nlicher Ansprechpartner <br> Susanne Sucko | <br> Wacker Neuson Linz GmbH Flughafenstra&szlig;e 7 , 4063 H&ouml;rsching http://www.wackerneuson.com/karriere</p>",
  "id": "b504c16830200e83",
  "status": "uncertain",
  "scrapedAt": "2026-07-03T06:35:36.560Z",
  "updatedAt": "2026-07-03T06:40:50.823Z",
  "match": null
}